Workbook

Sheet Dashboard
A1: Income Portfolio Dashboard
A2: Generated: 2026-03-30 | Goal: $2,000/month
A4: Portfolio Health Metrics
A5: Metric | B5: Value
A6: Portfolio Value (invested) | B6: =Holdings!G26-Holdings!G25 -> 0
A7: Portfolio Value (incl. cash) | B7: =Holdings!G26 -> 0
A8: Cash | B8: =Holdings!G25 -> 0
A9: Monthly Income | B9: =Holdings!M26 -> 0
A10: Annual Income | B10: =Holdings!L26 -> 0
A11: Portfolio Yield | B11: =IF(B6=0,0,B10/B6) -> 0
A12: Monthly Goal | B12: =Settings!B4 -> 2000
A13: Monthly Gap | B13: =B12-B9 -> 2000
A14: Income Achievement | B14: =IF(B12=0,0,B9/B12) -> 0
A17: Allocation & Drift
A18: Bucket | B18: Actual % | C18: Target % | D18: Drift | E18: Status
A19: Income Core | B19: =IF(B$6=0,0,SUMPRODUCT((Holdings!C$5:C$24=A19)*Holdings!G$5:G$24)/B$6) -> 0 | C19: =Allocation_Targets!B4 -> 0.4 | D19: =B19-C19 -> -0.4 | E19: =IF(ABS(D19)<=0.03,"Within tolerance",IF(ABS(D19)<=0.07,IF(D19>0,"OVERWEIGHT","UNDERWEIGHT"),IF(D19>0,"SEVERELY OVERWEIGHT","SEVERELY UNDERWEIGHT"))) -> SEVERELY UNDERWEIGHT
A20: High-Yield Stability | B20: =IF(B$6=0,0,SUMPRODUCT((Holdings!C$5:C$24=A20)*Holdings!G$5:G$24)/B$6) -> 0 | C20: =Allocation_Targets!B5 -> 0.3 | D20: =B20-C20 -> -0.3 | E20: =IF(ABS(D20)<=0.03,"Within tolerance",IF(ABS(D20)<=0.07,IF(D20>0,"OVERWEIGHT","UNDERWEIGHT"),IF(D20>0,"SEVERELY OVERWEIGHT","SEVERELY UNDERWEIGHT"))) -> SEVERELY UNDERWEIGHT
A21: Income Anchors | B21: =IF(B$6=0,0,SUMPRODUCT((Holdings!C$5:C$24=A21)*Holdings!G$5:G$24)/B$6) -> 0 | C21: =Allocation_Targets!B6 -> 0.2 | D21: =B21-C21 -> -0.2 | E21: =IF(ABS(D21)<=0.03,"Within tolerance",IF(ABS(D21)<=0.07,IF(D21>0,"OVERWEIGHT","UNDERWEIGHT"),IF(D21>0,"SEVERELY OVERWEIGHT","SEVERELY UNDERWEIGHT"))) -> SEVERELY UNDERWEIGHT
A22: Growth | B22: =IF(B$6=0,0,SUMPRODUCT((Holdings!C$5:C$24=A22)*Holdings!G$5:G$24)/B$6) -> 0 | C22: =Allocation_Targets!B7 -> 0.1 | D22: =B22-C22 -> -0.1 | E22: =IF(ABS(D22)<=0.03,"Within tolerance",IF(ABS(D22)<=0.07,IF(D22>0,"OVERWEIGHT","UNDERWEIGHT"),IF(D22>0,"SEVERELY OVERWEIGHT","SEVERELY UNDERWEIGHT"))) -> SEVERELY UNDERWEIGHT
A25: Income Progress & Time-to-Goal
A26: Scenario | B26: Monthly Savings | C26: Annual Deploy | D26: Years (current yield) | E26: Years (8% yield)
A27: Low | B27: 1500 | C27: =B27*12*0.6 -> 10800 | D27: =IF(B$11=0,"N/A",IF(C27=0,"N/A",(((Settings!B5)/B$11)-B$6)/C27)) -> N/A | E27: =IF(C27=0,"N/A",((Settings!B5/0.08)-B$6)/C27) -> 27.777778
A28: Mid | B28: 2000 | C28: =B28*12*0.7 -> 16800 | D28: =IF(B$11=0,"N/A",IF(C28=0,"N/A",(((Settings!B5)/B$11)-B$6)/C28)) -> N/A | E28: =IF(C28=0,"N/A",((Settings!B5/0.08)-B$6)/C28) -> 17.857143
A29: High | B29: 2500 | C29: =B29*12*0.75 -> 22500 | D29: =IF(B$11=0,"N/A",IF(C29=0,"N/A",(((Settings!B5)/B$11)-B$6)/C29)) -> N/A | E29: =IF(C29=0,"N/A",((Settings!B5/0.08)-B$6)/C29) -> 13.333333
A30: Aggressive | B30: 3000 | C30: =B30*12*0.8 -> 28800 | D30: =IF(B$11=0,"N/A",IF(C30=0,"N/A",(((Settings!B5)/B$11)-B$6)/C30)) -> N/A | E30: =IF(C30=0,"N/A",((Settings!B5/0.08)-B$6)/C30) -> 10.416667
A33: Income Concentration
A34: Metric | B34: Value
A35: Top 1 Income Contributor % | B35: =IF(B9=0,0,LARGE(Holdings!L5:L24,1)/B9) -> 0
A36: Top 3 Income Concentration % | B36: =IF(B9=0,0,(LARGE(Holdings!L5:L24,1)+LARGE(Holdings!L5:L24,2)+LARGE(Holdings!L5:L24,3))/B9) -> 0
A37: Number of Positions | B37: =COUNTA(Holdings!A5:A24) -> 0
A40: Macro & Market Signals
A41: Signal | B41: Value | C41: Implication
A42: 2yr Treasury | B42: =Settings!B9 -> 0.0396 | C42: Rate cut expectations
A43: 10yr Treasury | B43: =Settings!B10 -> 0.0441 | C43: Duration / yield curve
A44: VIX | B44: =Settings!B8 -> 31 | C44: Volatility regime
A45: HY OAS | B45: =Settings!B11 -> 0.0317 | C45: Credit spread health

Sheet Settings
A1: Income Portfolio Tracker — Settings
A3: Parameter | B3: Value | C3: Notes
A4: Monthly Income Goal | B4: 2000 | C4: Target passive income per month
A5: Annual Income Goal | B5: =B4*12 -> 24000 | C5: Calculated from monthly
A6: Portfolio Currency | B6: USD
A7: Risk-Free Rate | B7: 0.0441 | C7: 10yr Treasury yield — update weekly
A8: VIX Level | B8: 31 | C8: CBOE VIX — update weekly
A9: 2yr Treasury | B9: 0.0396 | C9: Fed H.15 — update weekly
A10: 10yr Treasury | B10: 0.0441 | C10: Fed H.15 — update weekly
A11: HY OAS | B11: 0.0317 | C11: ICE BofA HY OAS — update weekly
A12: Cash Reserve Min | B12: 1500 | C12: Minimum cash to keep in money market
A13: Report Start Date | B13: 46111 | C13: First report date
A14: Owner | B14: Shawn

Sheet Allocation_Targets
A1: Strategy Bucket Allocation Targets
A3: Bucket | B3: Target % | C3: Description | D3: Yield Range | E3: Income Type | F3: Example Tickers
A4: Income Core | B4: 0.4 | C4: Options-income & preferred ETFs | D4: 7-13% | E4: Variable + Stable | F4: JEPI, JEPQ, PFF, SPYI
A5: High-Yield Stability | B5: 0.3 | C5: BDCs, REITs, high-yield dividend | D5: 6-14% | E5: Stable + Variable | F5: ARCC, MAIN, O, MO, HTGC
A6: Income Anchors | B6: 0.2 | C6: Broad dividend ETFs, blue chips | D6: 2-4% | E6: Stable | F6: SCHD, VYM, HDV, XOM
A7: Growth | B7: 0.1 | C7: Growth with small dividend | D7: 0-2% | E7: Cyclical | F7: AAPL, MSFT, QQQ
A8: TOTAL | B8: =SUM(B4:B7) -> 1

Sheet Holdings
A1: Portfolio Holdings
A2: Blue cells = manual input | Black cells = formulas | Update prices & yields weekly
A4: Ticker | B4: Name | C4: Bucket | D4: Shares | E4: Avg Cost | F4: Current Price | G4: Market Value | H4: Cost Basis | I4: Unrealized G/L | J4: G/L % | K4: Annual Yield % | L4: Annual Income | M4: Monthly Income | N4: % of Portfolio
G5: =IF(D5="","",D5*F5) | H5: =IF(D5="","",D5*E5) | I5: =IF(G5="","",G5-H5) | J5: =IF(H5="","",IF(H5=0,0,I5/H5)) | L5: =IF(G5="","",G5*K5) | M5: =IF(L5="","",L5/12) | N5: =IF(G5="","",IF(G$26=0,0,G5/G$26))
G6: =IF(D6="","",D6*F6) | H6: =IF(D6="","",D6*E6) | I6: =IF(G6="","",G6-H6) | J6: =IF(H6="","",IF(H6=0,0,I6/H6)) | L6: =IF(G6="","",G6*K6) | M6: =IF(L6="","",L6/12) | N6: =IF(G6="","",IF(G$26=0,0,G6/G$26))
G7: =IF(D7="","",D7*F7) | H7: =IF(D7="","",D7*E7) | I7: =IF(G7="","",G7-H7) | J7: =IF(H7="","",IF(H7=0,0,I7/H7)) | L7: =IF(G7="","",G7*K7) | M7: =IF(L7="","",L7/12) | N7: =IF(G7="","",IF(G$26=0,0,G7/G$26))
G8: =IF(D8="","",D8*F8) | H8: =IF(D8="","",D8*E8) | I8: =IF(G8="","",G8-H8) | J8: =IF(H8="","",IF(H8=0,0,I8/H8)) | L8: =IF(G8="","",G8*K8) | M8: =IF(L8="","",L8/12) | N8: =IF(G8="","",IF(G$26=0,0,G8/G$26))
G9: =IF(D9="","",D9*F9) | H9: =IF(D9="","",D9*E9) | I9: =IF(G9="","",G9-H9) | J9: =IF(H9="","",IF(H9=0,0,I9/H9)) | L9: =IF(G9="","",G9*K9) | M9: =IF(L9="","",L9/12) | N9: =IF(G9="","",IF(G$26=0,0,G9/G$26))
G10: =IF(D10="","",D10*F10) | H10: =IF(D10="","",D10*E10) | I10: =IF(G10="","",G10-H10) | J10: =IF(H10="","",IF(H10=0,0,I10/H10)) | L10: =IF(G10="","",G10*K10) | M10: =IF(L10="","",L10/12) | N10: =IF(G10="","",IF(G$26=0,0,G10/G$26))
G11: =IF(D11="","",D11*F11) | H11: =IF(D11="","",D11*E11) | I11: =IF(G11="","",G11-H11) | J11: =IF(H11="","",IF(H11=0,0,I11/H11)) | L11: =IF(G11="","",G11*K11) | M11: =IF(L11="","",L11/12) | N11: =IF(G11="","",IF(G$26=0,0,G11/G$26))
G12: =IF(D12="","",D12*F12) | H12: =IF(D12="","",D12*E12) | I12: =IF(G12="","",G12-H12) | J12: =IF(H12="","",IF(H12=0,0,I12/H12)) | L12: =IF(G12="","",G12*K12) | M12: =IF(L12="","",L12/12) | N12: =IF(G12="","",IF(G$26=0,0,G12/G$26))
G13: =IF(D13="","",D13*F13) | H13: =IF(D13="","",D13*E13) | I13: =IF(G13="","",G13-H13) | J13: =IF(H13="","",IF(H13=0,0,I13/H13)) | L13: =IF(G13="","",G13*K13) | M13: =IF(L13="","",L13/12) | N13: =IF(G13="","",IF(G$26=0,0,G13/G$26))
G14: =IF(D14="","",D14*F14) | H14: =IF(D14="","",D14*E14) | I14: =IF(G14="","",G14-H14) | J14: =IF(H14="","",IF(H14=0,0,I14/H14)) | L14: =IF(G14="","",G14*K14) | M14: =IF(L14="","",L14/12) | N14: =IF(G14="","",IF(G$26=0,0,G14/G$26))
G15: =IF(D15="","",D15*F15) | H15: =IF(D15="","",D15*E15) | I15: =IF(G15="","",G15-H15) | J15: =IF(H15="","",IF(H15=0,0,I15/H15)) | L15: =IF(G15="","",G15*K15) | M15: =IF(L15="","",L15/12) | N15: =IF(G15="","",IF(G$26=0,0,G15/G$26))
G16: =IF(D16="","",D16*F16) | H16: =IF(D16="","",D16*E16) | I16: =IF(G16="","",G16-H16) | J16: =IF(H16="","",IF(H16=0,0,I16/H16)) | L16: =IF(G16="","",G16*K16) | M16: =IF(L16="","",L16/12) | N16: =IF(G16="","",IF(G$26=0,0,G16/G$26))
... G24: =IF(D24="","",D24*F24) | H24: =IF(D24="","",D24*E24) | I24: =IF(G24="","",G24-H24) | J24: =IF(H24="","",IF(H24=0,0,I24/H24)) | L24: =IF(G24="","",G24*K24) | M24: =IF(L24="","",L24/12) | N24: =IF(G24="","",IF(G$26=0,0,G24/G$26))
A25: SWVXX | B25: Schwab Money Market | C25: Cash | E25: 1 | F25: 0 | G25: =F25 -> 0 | K25: 0.042 | L25: =G25*K25 -> 0 | M25: =L25/12 -> 0
A26: TOTAL | G26: =SUM(G5:G25) -> 0 | H26: =SUM(H5:H24) -> 0 | I26: =SUM(I5:I24) -> 0 | J26: =IF(H26=0,0,I26/H26) -> 0 | L26: =SUM(L5:L25) -> 0 | M26: =SUM(M5:M25) -> 0 | N26: =IF(G26=0,0,SUM(G5:G24)/G26) -> 0

Sheet Weekly_Log
A1: Weekly Snapshot Log
A2: Add a row each week to track trends over time
A4: Date | B4: Portfolio Value | C4: Cash | D4: Monthly Income | E4: Yield % | F4: Income Core % | G4: HY Stability % | H4: Anchors % | I4: Growth % | J4: Notes

Sheet Watchlist
A1: Watchlist & Research
A3: Ticker | B3: Name | C3: Bucket | D3: Yield % | E3: Price | F3: Notes | G3: Action
